{
  "db_name": "PostgreSQL",
  "query": "DELETE FROM task WHERE id = $1 RETURNING *",
  "describe": {
    "columns": [
      {
        "ordinal": 0,
        "name": "id",
        "type_info": "Uuid"
      },
      {
        "ordinal": 1,
        "name": "title",
        "type_info": "Text"
      },
      {
        "ordinal": 2,
        "name": "description",
        "type_info": "Text"
      },
      {
        "ordinal": 3,
        "name": "deadline",
        "type_info": "Timestamptz"
      },
      {
        "ordinal": 4,
        "name": "completed",
        "type_info": "Bool"
      },
      {
        "ordinal": 5,
        "name": "user_id",
        "type_info": "Uuid"
      },
      {
        "ordinal": 6,
        "name": "community_id",
        "type_info": "Uuid"
      }
    ],
    "parameters": {
      "Left": [
        "Uuid"
      ]
    },
    "nullable": [
      false,
      false,
      false,
      true,
      false,
      false,
      true
    ]
  },
  "hash": "c523500f9fa67f2a8f96052e2a87929bc09e8ec18d0ef1379e14758145977bc5"
}
